kkconfig/local.py
kkconfig/runconfig.py
kkconfig-0.0.2.dist-info/LICENSE
kkconfig-0.0.2.dist-info/METADATA
kkconfig-0.0.2.dist-info/WHEEL
kkconfig-0.0.2.dist-info/top_level.txt
kkconfig-0.0.2.dist-info/RECORD
